mastml/__init__.py
mastml/baseline_tests.py
mastml/data_cleaning.py
mastml/data_splitters.py
mastml/datasets.py
mastml/domain.py
mastml/error_analysis.py
mastml/feature_generators.py
mastml/feature_selectors.py
mastml/hyper_opt.py
mastml/learning_curve.py
mastml/mastml.py
mastml/mastml_predictor.py
mastml/metrics.py
mastml/models.py
mastml/plots.py
mastml/preprocessing.py
mastml/data/diffusion_data_allfeatures.xlsx
mastml/data/diffusion_data_leaveoutPt.xlsx
mastml/data/diffusion_data_nofeatures.xlsx
mastml/data/diffusion_data_selectfeatures.xlsx
mastml/magpie/AtomicNumber.table
mastml/magpie/AtomicRadii.table
mastml/magpie/AtomicVolume.table
mastml/magpie/AtomicWeight.table
mastml/magpie/BCCefflatcnt.table
mastml/magpie/BCCenergy_pa.table
mastml/magpie/BCCfermi.table
mastml/magpie/BCCmagmom.table
mastml/magpie/BCCvolume_pa.table
mastml/magpie/BCCvolume_padiff.table
mastml/magpie/BoilingT.table
mastml/magpie/BulkModulus.table
mastml/magpie/Column.table
mastml/magpie/CovalentRadii.table
mastml/magpie/CovalentRadius.table
mastml/magpie/Density.table
mastml/magpie/ElasticModulus.table
mastml/magpie/ElectricalConductivity.table
mastml/magpie/ElectronAffinity.table
mastml/magpie/Electronegativity.table
mastml/magpie/FirstIonizationEnergy.table
mastml/magpie/GSbandgap.table
mastml/magpie/GSenergy_pa.table
mastml/magpie/GSestBCClatcnt.table
mastml/magpie/GSestFCClatcnt.table
mastml/magpie/GSmagmom.table
mastml/magpie/GSvolume_pa.table
mastml/magpie/Group.table
mastml/magpie/HHIp.table
mastml/magpie/HHIr.table
mastml/magpie/HeatCapacityMass.table
mastml/magpie/HeatCapacityMolar.table
mastml/magpie/HeatFusion.table
mastml/magpie/HeatVaporization.table
mastml/magpie/ICSDVolume.table
mastml/magpie/IonicRadii.table
mastml/magpie/IonizationEnergy.table
mastml/magpie/IsAlkali.table
mastml/magpie/IsAlkalineEarth.table
mastml/magpie/IsBCC.table
mastml/magpie/IsBoron.table
mastml/magpie/IsCarbon.table
mastml/magpie/IsChalcogen.table
mastml/magpie/IsDBlock.table
mastml-3.2.5.dist-info/LICENSE
mastml-3.2.5.dist-info/METADATA
mastml-3.2.5.dist-info/WHEEL
mastml-3.2.5.dist-info/top_level.txt
mastml-3.2.5.dist-info/RECORD
