Metadata-Version: 2.1
Name: mastml
Version: 3.2.5
Summary: MAterials Simulation Toolkit - Machine Learning
Home-page: https://github.com/uw-cmg/MAST-ML
Author: MAST Development Team, University of Wisconsin-Madison Computational Materials Group
Author-email: ddmorgan@wisc.edu
License: MIT
Keywords: MAST,materials,simulation,MASTML,machine learning
License-File: LICENSE
Requires-Dist: scikit-learn
Requires-Dist: scikit-optimize
Requires-Dist: matminer
Requires-Dist: matplotlib
Requires-Dist: mdf-forge
Requires-Dist: mdf-toolbox
Requires-Dist: numpy
Requires-Dist: openpyxl
Requires-Dist: pandas
Requires-Dist: pathos
Requires-Dist: pykan==0.0.5
Requires-Dist: pymatgen
Requires-Dist: pyyaml
Requires-Dist: scipy
Requires-Dist: shap
Requires-Dist: sphinx-automodapi
Requires-Dist: sphinx-rtd-theme
Requires-Dist: statsmodels
Requires-Dist: madml
Requires-Dist: udocker
Requires-Dist: transfernet
Requires-Dist: forestci
